tiresia/__init__.py
tiresia/predictor.py
tiresia/utils.py
tiresia-0.0.11.dist-info/LICENSE
tiresia-0.0.11.dist-info/METADATA
tiresia-0.0.11.dist-info/WHEEL
tiresia-0.0.11.dist-info/top_level.txt
tiresia-0.0.11.dist-info/RECORD
