Metadata-Version: 2.1
Name: tiresia
Version: 0.0.11
Summary: Tiny sklearn-based AutoML tool.
Home-page: https://github.com/nicomignoni/tiresia
Author: Nicola Mignoni
Author-email: nicola.mignoni@gmail.com
License: UNKNOWN
Platform: UNKNOWN
Classifier: Programming Language :: Python :: 3
Classifier: License :: OSI Approved :: MIT License
Classifier: Operating System :: OS Independent
Requires-Python: >=3.6
